cdk_datadog_resources/__init__.py
cdk_datadog_resources/py.typed
cdk_datadog_resources/_jsii/__init__.py
cdk_datadog_resources/_jsii/cdk-datadog-resources@0.2.43.jsii.tgz
cdk_datadog_resources-0.2.43.dist-info/LICENSE
cdk_datadog_resources-0.2.43.dist-info/METADATA
cdk_datadog_resources-0.2.43.dist-info/WHEEL
cdk_datadog_resources-0.2.43.dist-info/top_level.txt
cdk_datadog_resources-0.2.43.dist-info/RECORD
